smart_boiler/__init__.py
smart_boiler/boiler.py
smart_boiler/control.py
smart_boiler/event_checker.py
smart_boiler/time_handler.py
smart_boiler/web_server.py
smart_boiler/week_planner.py
smart_boiler/static/style.css
smart_boiler/templates/index.html
smart_boiler-0.0.1.3.6.dist-info/METADATA
smart_boiler-0.0.1.3.6.dist-info/WHEEL
smart_boiler-0.0.1.3.6.dist-info/top_level.txt
smart_boiler-0.0.1.3.6.dist-info/RECORD
