Metadata-Version: 2.1
Name: smart-boiler
Version: 0.0.1.3.6
Summary: Smart boiling of household
Home-page: https://github.com/grinwi/smart_boiler
Author: Adam GRUNWALD
Author-email: grunwald.adam24@gmail.com
Keywords: energy,management,optimization,hass
Classifier: Development Status :: 5 - Production/Stable
Classifier: Intended Audience :: Developers
Classifier: Topic :: Software Development :: Build Tools
Classifier: License :: OSI Approved :: MIT License
Classifier: Programming Language :: Python :: 3.10
Classifier: Operating System :: OS Independent
Requires-Python: >=3.9, <=3.10
Requires-Dist: wheel
Requires-Dist: numpy ==1.22.2
Requires-Dist: scipy <1.9.0
Requires-Dist: pandas ==1.4.1
Requires-Dist: pvlib >=0.10.1
Requires-Dist: protobuf >=3.0.0
Requires-Dist: pytz >=2021.1
Requires-Dist: requests >=2.25.1
Requires-Dist: beautifulsoup4 >=4.9.3
Requires-Dist: pulp >=2.4
Requires-Dist: pyyaml >=5.4.1
Requires-Dist: tables ==3.7.0
Requires-Dist: skforecast ==0.10.1
